{
	"info": {
		"_postman_id": "4ba140e3-13ba-4586-8ec6-ba9dbd67883a",
		"name": "NZWalks",
		"schema": "https://schema.getpostman.com/json/collection/v2.1.0/collection.json",
		"_exporter_id": "25311935"
	},
	"item": [
		{
			"name": "Region",
			"item": [
				{
					"name": "Get All Regions",
					"request": {
						"method": "GET",
						"header": [],
						"url": {
							"raw": "http://localhost:5275/api/regions",
							"protocol": "http",
							"host": [
								"localhost"
							],
							"port": "5275",
							"path": [
								"api",
								"regions"
							]
						}
					},
					"response": []
				},
				{
					"name": "Post Region",
					"request": {
						"method": "POST",
						"header": [],
						"body": {
							"mode": "raw",
							"raw": "{\n    \"code\": \"WLG\",\n    \"name\": \"Wellington Region\",\n    \"regionImageUrl\": \"https://images.pexels.com/photos/4350631/pexels-photo-4350631.jpeg?auto=compress&cs=tinysrgb&w=1260&h=750\"\n}",
							"options": {
								"raw": {
									"language": "json"
								}
							}
						},
						"url": {
							"raw": "http://localhost:5275/api/regions",
							"protocol": "http",
							"host": [
								"localhost"
							],
							"port": "5275",
							"path": [
								"api",
								"regions"
							]
						}
					},
					"response": []
				},
				{
					"name": "Update Region",
					"request": {
						"method": "PUT",
						"header": [],
						"body": {
							"mode": "raw",
							"raw": "{\n    \"code\": \"WLG\",\n    \"name\": \"Wellington Region\",\n    \"regionImageUrl\": \"https://images.pexels.com/photos/4350631/pexels-photo-4350631.jpeg?auto=compress&cs=tinysrgb&w=1260&h=750\"\n}",
							"options": {
								"raw": {
									"language": "json"
								}
							}
						},
						"url": {
							"raw": "http://localhost:5275/api/regions/08dda1d5-8e52-4440-8ad0-f2b99350f323",
							"protocol": "http",
							"host": [
								"localhost"
							],
							"port": "5275",
							"path": [
								"api",
								"regions",
								"08dda1d5-8e52-4440-8ad0-f2b99350f323"
							]
						}
					},
					"response": []
				},
				{
					"name": "Get Region By ID",
					"request": {
						"method": "GET",
						"header": [],
						"url": {
							"raw": "http://localhost:5275/api/regions/08dda1d5-8e52-4440-8ad0-f2b99350f323",
							"protocol": "http",
							"host": [
								"localhost"
							],
							"port": "5275",
							"path": [
								"api",
								"regions",
								"08dda1d5-8e52-4440-8ad0-f2b99350f323"
							]
						}
					},
					"response": []
				},
				{
					"name": "Delete Region",
					"request": {
						"method": "DELETE",
						"header": [],
						"url": {
							"raw": "http://localhost:5275/api/regions/08dda1d5-8e52-4440-8ad0-f2b99350f323",
							"protocol": "http",
							"host": [
								"localhost"
							],
							"port": "5275",
							"path": [
								"api",
								"regions",
								"08dda1d5-8e52-4440-8ad0-f2b99350f323"
							]
						}
					},
					"response": []
				}
			]
		},
		{
			"name": "Walk",
			"item": [
				{
					"name": "Get All Walks",
					"request": {
						"method": "GET",
						"header": [],
						"url": {
							"raw": "http://localhost:5275/api/walks",
							"protocol": "http",
							"host": [
								"localhost"
							],
							"port": "5275",
							"path": [
								"api",
								"walks"
							]
						}
					},
					"response": []
				},
				{
					"name": "Post Walk",
					"request": {
						"method": "POST",
						"header": [],
						"body": {
							"mode": "raw",
							"raw": "{\n    \"name\": \"Mount Victoria Lookout Walk\",\n    \"description\": \"This is an easy 20 - 30 minutes walk to the lookout, which offers panoramic view of Wellington city, harbour and the sorroundings hills\",\n    \"lenghtInKm\": 5,\n    \"walkImageUrl\": null,\n    \"difficultyId\": \"0d2cb1db-b382-44ae-84c3-39709c98b1a2\",\n    \"regionId\": \"1a8c15d1-d98c-48cf-8288-cc539e6338e6\"\n}",
							"options": {
								"raw": {
									"language": "json"
								}
							}
						},
						"url": {
							"raw": "http://localhost:5275/api/walks",
							"protocol": "http",
							"host": [
								"localhost"
							],
							"port": "5275",
							"path": [
								"api",
								"walks"
							]
						}
					},
					"response": []
				},
				{
					"name": "Update Walk",
					"request": {
						"method": "PUT",
						"header": [],
						"body": {
							"mode": "raw",
							"raw": "{\n    \"name\": \"Mount Victoria Lookout Walk2\",\n    \"description\": \"This is an easy 20 - 30 minutes walk to the lookout, which offers panoramic view of Wellington city, harbour and the sorroundings hills\",\n    \"lenghtInKm\": 5,\n    \"walkImageUrl\": null,\n    \"difficultyId\": \"0d2cb1db-b382-44ae-84c3-39709c98b1a2\",\n    \"regionId\": \"1a8c15d1-d98c-48cf-8288-cc539e6338e6\"\n}",
							"options": {
								"raw": {
									"language": "json"
								}
							}
						},
						"url": {
							"raw": "http://localhost:5275/api/walks/08ddba3a-563f-43ff-808e-1663426dfc9d",
							"protocol": "http",
							"host": [
								"localhost"
							],
							"port": "5275",
							"path": [
								"api",
								"walks",
								"08ddba3a-563f-43ff-808e-1663426dfc9d"
							]
						}
					},
					"response": []
				},
				{
					"name": "Get Walk By ID",
					"request": {
						"method": "GET",
						"header": [],
						"url": {
							"raw": "http://localhost:5275/api/walks/08ddba3a-563f-43ff-808e-1663426dfc9d",
							"protocol": "http",
							"host": [
								"localhost"
							],
							"port": "5275",
							"path": [
								"api",
								"walks",
								"08ddba3a-563f-43ff-808e-1663426dfc9d"
							]
						}
					},
					"response": []
				},
				{
					"name": "Delete Walk",
					"request": {
						"method": "DELETE",
						"header": [],
						"url": {
							"raw": "http://localhost:5275/api/walks/08dda1d5-8e52-4440-8ad0-f2b99350f323",
							"protocol": "http",
							"host": [
								"localhost"
							],
							"port": "5275",
							"path": [
								"api",
								"walks",
								"08dda1d5-8e52-4440-8ad0-f2b99350f323"
							]
						}
					},
					"response": []
				}
			]
		},
		{
			"name": "Auth",
			"item": [
				{
					"name": "Register user",
					"request": {
						"method": "POST",
						"header": [],
						"body": {
							"mode": "raw",
							"raw": "{\n    \"username\": \"reader@nzwalks.com\",\n    \"password\": \"Reader@123\",\n    \"roles\": [\n        \"Reader\"\n    ]\n}",
							"options": {
								"raw": {
									"language": "json"
								}
							}
						},
						"url": {
							"raw": "http://localhost:5275/api/auth/register",
							"protocol": "http",
							"host": [
								"localhost"
							],
							"port": "5275",
							"path": [
								"api",
								"auth",
								"register"
							]
						}
					},
					"response": []
				},
				{
					"name": "Login",
					"request": {
						"method": "POST",
						"header": [],
						"body": {
							"mode": "raw",
							"raw": "{\n    \"username\": \"reader@nzwalks.com\",\n    \"password\": \"Reader@123\"\n}",
							"options": {
								"raw": {
									"language": "json"
								}
							}
						},
						"url": {
							"raw": "http://localhost:5275/api/auth/login",
							"protocol": "http",
							"host": [
								"localhost"
							],
							"port": "5275",
							"path": [
								"api",
								"auth",
								"login"
							]
						}
					},
					"response": []
				}
			]
		}
	]
}